{"URL":"https://www.banque-france.fr/sites/default/files/medias/documents/declaration_francois_villeroy_de_galhau_-_bitcoin_-_fr.pdf","TITLE":"Déclaration : « Le bitcoin n\u0027est en rien une monnaie, ou même une crypto monnaie. »","DATE":"01.12.2017","TEXT":"1 \n \n \n \n \nDéclaration de François Villeroy de Galhau,  \ngouverneur de la Banque de France  \nPékin, 1\ner\n décembre 2017 \n Bitcoin \n \n« Je voudrais d\u0027abord dire quelques mots sur le bitcoin, sujet de grande attention \nparticulièrement ici en Chine. Il est associé à une technologie utile, celle de la blockchain  \net des registres distribués (ou Distributed Ledger Technology). La Banque de France, \ncomme d\u0027autres acteurs, expérimente cette technologie innovante. \nMais au-delà, il ne doit pas y avoir d\u0027ambiguïté : le bitcoin n\u0027est en rien une monnaie ,  \nou même une crypto monnaie. C\u0027est un actif spéculatif. Sa valeur et sa forte volatilité  \nne correspondent à aucun sous-jacent économique et ne sont la responsabilité de personne. \nLa Banque de France tient à rappeler que ceux qui investissent en bitcoin le font totalement \nà leurs risques et périls.  \nNous avons noté par ailleurs avec intérêt les mesures prises par les autorités chinoises \nconcernant les ICO. » \n  \n","SECTION":"discours"}